<?xml version="1.0" encoding="UTF-8"?>
<objects serializationModel="Studio.02.01.00">
	<object class="AudioFile" id="{05c74351-5452-4bf3-bea6-78aaadbe761c}">
		<property name="assetPath">
			<value>Elephant/Enemy_Elephant_Hurt_04.wav</value>
		</property>
		<property name="frequencyInKHz">
			<value>48</value>
		</property>
		<property name="channelCount">
			<value>1</value>
		</property>
		<property name="length">
			<value>0.95552083333333337</value>
		</property>
		<relationship name="masterAssetFolder">
			<destination>{395e9745-639d-43d7-bc73-6a7bdf41f2ac}</destination>
		</relationship>
	</object>
</objects>
